torchlop/__init__.py
torchlop/count_hooks.py
torchlop/nlp_hooks.py
torchlop/profile.py
torchlop/rst_process.py
torchlop/utils.py
torchlop-0.2.dist-info/LICENSE
torchlop-0.2.dist-info/METADATA
torchlop-0.2.dist-info/WHEEL
torchlop-0.2.dist-info/top_level.txt
torchlop-0.2.dist-info/zip-safe
torchlop-0.2.dist-info/RECORD
