Metadata-Version: 2.1
Name: torchlop
Version: 0.2
Summary: A tool to layer-wise count the MACs and parameters of PyTorch model.
Home-page: https://github.com/hahnyuan/pytorch-layerwise-OpCounter/
Author: Hahn Yuan
Author-email: yuanzhihang1@126.com
License: MIT
Platform: UNKNOWN
Classifier: Programming Language :: Python :: 3
Requires-Dist: torch
